remove_duplicate_armaaan_alam_123/__init__.py
remove_duplicate_armaaan_alam_123/impoting.py
remove_duplicate_armaaan_alam_123/list_operations.py
remove_duplicate_armaaan_alam_123/main.py
remove_duplicate_armaaan_alam_123-0.3.dist-info/METADATA
remove_duplicate_armaaan_alam_123-0.3.dist-info/WHEEL
remove_duplicate_armaaan_alam_123-0.3.dist-info/license.txt
remove_duplicate_armaaan_alam_123-0.3.dist-info/top_level.txt
remove_duplicate_armaaan_alam_123-0.3.dist-info/RECORD
