Metadata-Version: 2.1
Name: remove_duplicate_armaaan_alam_123
Version: 0.3
Summary: remove_duplicate and flatten_list
License-File: license.txt
